<?xml version="1.0"?>
<opencv_storage>
<cascade>
  <stageType>BOOST</stageType>
  <featureType>LBP</featureType>
  <height>18</height>
  <width>36</width>
  <stageParams>
    <boostType>GAB</boostType>
    <minHitRate>9.9500000476837158e-01</minHitRate>
    <maxFalseAlarm>5.0000000000000000e-01</maxFalseAlarm>
    <weightTrimRate>9.4999999999999996e-01</weightTrimRate>
    <maxDepth>1</maxDepth>
    <maxWeakCount>100</maxWeakCount></stageParams>
  <featureParams>
    <maxCatCount>256</maxCatCount>
    <featSize>1</featSize></featureParams>
  <stageNum>16</stageNum>
  <stages>
    <!-- stage 0 -->
    <_>
      <maxWeakCount>5</maxWeakCount>
      <stageThreshold>-1.0164581537246704e+00</stageThreshold>
      <weakClassifiers>
        <_>
          <internalNodes>
            0 -1 121 -2101490 8645451 -283130880 -521148469 -204483069
            12806163 -87825664 -134217729</internalNodes>
          <leafValues>
            -6.9118094444274902e-01 5.3935295343399048e-01</leafValues></_>
        <_>
          <internalNodes>
            0 -1 10 -279974098 -496242961 -1069413754 -393288982
            1933003556 1107542979 1930908736 -137887881</internalNodes>
          <leafValues>
            -6.3112831115722656e-01 5.1992321014404297e-01</leafValues></_>
        <_>
          <internalNodes>
            0 -1 22 35655605 -827433 -5415457 -36391040 1874996219
            -34146 -275874833 706740768</internalNodes>
          <leafValues>
            -6.8107974529266357e-01 5.0729984045028687e-01</leafValues></_>
        <_>
          <internalNodes>
            0 -1 45 905461180 1071454716 -1190553121 -1107455523
            -3604483 969733017 -1229826 1001921916</internalNodes>
          <leafValues>
            -6.8964874744415283e-01 4.4974544644355774e-01</leafValues></_>
        <_>
          <internalNodes>
            0 -1 73 -83890686 -2137546038 16777224 -1060960242 952574500
            46351119 -801677308 1400893103</internalNodes>
          <leafValues>
            -5.9438413381576538e-01 5.3718543052673340e-01</leafValues></_></weakClassifiers></_>
    <!-- stage 1 -->
    <_>
      <maxWeakCount>3</maxWeakCount>
      <stageThreshold>-9.6158474683761597e-01</stageThreshold>
      <weakClassifiers>
        <_>
          <internalNodes>
            0 -1 7 -342891990 -858787222 -993861598 -420558910
            1895973654 1112604759 -1021099775 -143132809</internalNodes>
          <leafValues>
            -8.1113457679748535e-01 4.5976096391677856e-01</leafValues></_>
        <_>
          <internalNodes>
            0 -1 108 -335813114 -529607678 5522944 1084412484 1620529409
            1076093571 -981147648 -201327637</internalNodes>
          <leafValues>
            -7.1228593587875366e-01 5.3981220722198486e-01</leafValues></_>
        <_>
          <internalNodes>
            0 -1 49 5136 269795672 -1861144515 -1076422671 -611597063
            -1149220182 -1585173830 -1141147489</internalNodes>
          <leafValues>
            -6.3254243135452271e-01 5.6183582544326782e-01</leafValues></_></weakClassifiers></_>
    <!-- stage 2 -->
    <_>
      <maxWeakCount>5</maxWeakCount>
      <stageThreshold>-1.0309549570083618e+00</stageThreshold>
      <weakClassifiers>
        <_>
          <internalNodes>
            0 -1 51 268437744 290500948 -1114719811 -6704805 -1618149379
            -1076078413 -357921859 -1078915093</internalNodes>
          <leafValues>
            -7.1921354532241821e-01 3.8260513544082642e-01</leafValues></_>
        <_>
          <internalNodes>
            0 -1 122 -17830386 13563031 -953434100 -2008231014
            -220995577 1076482227 -637821440 -789577749</internalNodes>
          <leafValues>
            -6.3529521226882935e-01 4.3188422918319702e-01</leafValues></_>
        <_>
          <internalNodes>
            0 -1 36 496508412 -1653307174 957356029 1071120604 314050812
            -72849222 724646911 458762496</internalNodes>
          <leafValues>
            -7.2846937179565430e-01 3.9699622988700867e-01</leafValues></_>
        <_>
          <internalNodes>
            0 -1 81 -2643238 931172412 4194440 990384812 172499336
            574624745 964690924 -134220801</internalNodes>
          <leafValues>
            -4.9917802214622498e-01 5.5823230743408203e-01</leafValues></_>
        <_>
          <internalNodes>
            0 -1 60 819200221 -545819180 -786991361 -543199009
            -1165378309 -1145372421 -762590469 -1367855576</internalNodes>
          <leafValues>
            -5.7338857650756836e-01 5.2183729410171509e-01</leafValues></_></weakClassifiers></_>
    <!-- stage 3 -->
    <_>
      <maxWeakCount>6</maxWeakCount>
      <stageThreshold>-1.3750067949295044e+00</stageThreshold>
      <weakClassifiers>
        <_>
          <internalNodes>
            0 -1 86 -1073225214 -745282173 1611024547 -682630394
            -233847825 -1038097918 -455611717 -1060641149</internalNodes>
          <leafValues>
            -6.2025314569473267e-01 4.0825036168098450e-01</leafValues></_>
        <_>
          <internalNodes>
            0 -1 43 876613916 -40037089 -783166017 -8432889 -1171594753
            -4274039 -133657938 -1467482104</internalNodes>
          <leafValues>
            -5.8861476182937622e-01 4.7982457280158997e-01</leafValues></_>
        <_>
          <internalNodes>
            0 -1 6 -336597458 -490215229 -1058878458 -489764182
            1668641655 1393971207 -217128362 -134745097</internalNodes>
          <leafValues>
            -5.6835436820983887e-01 4.8286029696464539e-01</leafValues></_>
        <_>
          <internalNodes>
            0 -1 20 79692020 534677841 424218623 1070072336 268704925
            -73329762 -1079369730 -1073909782</internalNodes>
          <leafValues>
            -6.0406535863876343e-01 4.6269953250885010e-01</leafValues></_>
        <_>
          <internalNodes>
            0 -1 97 -21330 421536498 -1342363608 -214028566 1836585004
            286537041 1865875704 -1025</internalNodes>
          <leafValues>
            -4.6817129850387573e-01 5.8012592792510986e-01</leafValues></_>
        <_>
          <internalNodes>
            0 -1 63 909651700 -2612866 -1081069153 -1084489636 839925759
            -1079235939 998865919 -1111744804</internalNodes>
          <leafValues>
            -6.2081623077392578e-01 4.2852258682250977e-01</leafValues></_></weakClassifiers></_>
    <!-- stage 4 -->
    <_>
      <maxWeakCount>7</maxWeakCount>
      <stageThreshold>-1.3817892074584961e+00</stageThreshold>
      <weakClassifiers>
        <_>
          <internalNodes>
            0 -1 90 -1073233918 -7867830 1774438879 -174071546
            -487591697 -353447872 1630530447 -795351289</internalNodes>
          <leafValues>
            -6.0853856801986694e-01 3.0612245202064514e-01</leafValues></_>
        <_>
          <internalNodes>
            0 -1 27 -866087472 -47148812 1543519733 -538179376 178522620
            -1091040067 -1966043204 -1428943612</internalNodes>
          <leafValues>
            -5.7823383808135986e-01 3.8258698582649231e-01</leafValues></_>
        <_>
          <internalNodes>
            0 -1 37 289739038 2134880727 -1687055361 2138284927
            -1738673666 -8005187 1509787391 172952264</internalNodes>
          <leafValues>
            -6.0462307929992676e-01 3.4132298827171326e-01</leafValues></_>
        <_>
          <internalNodes>
            0 -1 112 -1063522814 1090515890 -987518497 -975187365
            -666902270 -2004358237 -456460858 14679803</internalNodes>
          <leafValues>
            -5.6259483098983765e-01 4.1315501928329468e-01</leafValues></_>
        <_>
          <internalNodes>
            0 -1 71 893136892 424984573 -641843717 -1078150900
            2109476861 -1154906888 -1079493636 1056454904</internalNodes>
          <leafValues>
            -7.5118625164031982e-01 2.5987851619720459e-01</leafValues></_>
        <_>
          <internalNodes>
            0 -1 77 -1060641790 2002240806 -258542561 -578727421
            -292822385 -1878916986 -800094261 -1068244437</internalNodes>
          <leafValues>
            -4.5728075504302979e-01 4.6161931753158569e-01</leafValues></_>
        <_>
          <internalNodes>
            0 -1 28 12912 2002213853 1558175231 -1256749681 -1424237825
            -103100885 -410259713 4653568</internalNodes>
          <leafValues>
            -6.8373686075210571e-01 2.8601825237274170e-01</leafValues></_></weakClassifiers></_>
    <!-- stage 5 -->
    <_>
      <maxWeakCount>7</maxWeakCount>
      <stageThreshold>-1.0901353359222412e+00</stageThreshold>
      <weakClassifiers>
        <_>
          <internalNodes>
            0 -1 92 -3163938 396397186 -1122500432 1003139974 2041847944
            271073553 332334300 2147483647</internalNodes>
          <leafValues>
            -7.0157480239868164e-01 2.2578348219394684e-01</leafValues></_>
        <_>
          <internalNodes>
            0 -1 120 -268440822 4184991 -674370816 1659876317 -370410686
            2000418299 -84149504 -252706881</internalNodes>
          <leafValues>
            -6.0130935907363892e-01 3.3310183882713318e-01</leafValues></_>
        <_>
          <internalNodes>
            0 -1 42 -1039941118 -217616093 1615063327 -241712605
            -687289430 -1144354306 -334762162 -1066932381</internalNodes>
          <leafValues>
            -4.4966760277748108e-01 4.6698939800262451e-01</leafValues></_>
        <_>
          <internalNodes>
            0 -1 68 -2122284912 -1090455534 -1681680995 1070641104
            -20972611 -1078224767 -1410137411 -1343018573</internalNodes>
          <leafValues>
            -5.3551906347274780e-01 3.7870019674301147e-01</leafValues></_>
        <_>
          <internalNodes>
            0 -1 88 -1070450 870985048 42139824 996573700 -1106765700
            201873562 1743410140 1540358111</internalNodes>
          <leafValues>
            -5.2978163957595825e-01 3.6144843697547913e-01</leafValues></_>
        <_>
          <internalNodes>
            0 -1 31 -1939853392 -577122062 1502616063 1599219130
            227580924 -914321004 -370630673 214173504</internalNodes>
          <leafValues>
            -6.0552209615707397e-01 3.4924620389938354e-01</leafValues></_>
        <_>
          <internalNodes>
            0 -1 126 -541065224 422115384 -1057384 -1090060358
            -1673538307 -1438728201 2113920252 -15467077</internalNodes>
          <leafValues>
            -3.8117402791976929e-01 5.2778989076614380e-01</leafValues></_></weakClassifiers></_>
    <!-- stage 6 -->
    <_>
      <maxWeakCount>8</maxWeakCount>
      <stageThreshold>-1.3476891517639160e+00</stageThreshold>
      <weakClassifiers>
        <_>
          <internalNodes>
            0 -1 11 -286265649 -287390017 -827683226 -290536562
            1395093845 1931956081 -285903036 -134744073</internalNodes>
          <leafValues>
            -6.2529915571212769e-01 2.8105655312538147e-01</leafValues></_>
        <_>
          <internalNodes>
            0 -1 56 -1071127037 -50863125 -289407402 -239343617
            -147853846 -1018253502 -1062801473 -800590013</internalNodes>
          <leafValues>
            -3.9758357405662537e-01 5.0723552703857422e-01</leafValues></_>
        <_>
          <internalNodes>
            0 -1 33 -2080373888 -546589771 -171995141 -2638918
            -342044931 -1062913 -1177818178 -1977612032</internalNodes>
          <leafValues>
            -5.8244431018829346e-01 3.3762589097023010e-01</leafValues></_>
        <_>
          <internalNodes>
            0 -1 75 -356520186 615433775 -307301214 -529603718
            1675579941 1194556139 -172625312 -167774209</internalNodes>
          <leafValues>
            -5.1843309402465820e-01 3.6296874284744263e-01</leafValues></_>
        <_>
          <internalNodes>
            0 -1 23 2097328 -4262985 -1538521673 -1216114040 1662518268
            -18070610 -1920135429 -271626369</internalNodes>
          <leafValues>
            -4.2509132623672485e-01 4.5544615387916565e-01</leafValues></_>
        <_>
          <internalNodes>
            0 -1 5 -294688977 -472912437 1799466506 -353440566 655565423
            850647851 1444407287 -164628619</internalNodes>
          <leafValues>
            -4.9901044368743896e-01 3.8141638040542603e-01</leafValues></_>
        <_>
          <internalNodes>
            0 -1 110 83345431 12774355 -251191905 -2231585 -525861961
            1506648762 -1997276758 -2065699353</internalNodes>
          <leafValues>
            -4.2755702137947083e-01 4.3639278411865234e-01</leafValues></_>
        <_>
          <internalNodes>
            0 -1 48 1358977424 -1791707260 -81636387 -6754249 -106832451
            -111112061 -979761441 -1085463894</internalNodes>
          <leafValues>
            -5.1844465732574463e-01 3.5742419958114624e-01</leafValues></_></weakClassifiers></_>
    <!-- stage 7 -->
    <_>
      <maxWeakCount>8</maxWeakCount>
      <stageThreshold>-1.6724135875701904e+00</stageThreshold>
      <weakClassifiers>
        <_>
          <internalNodes>
            0 -1 123 -209 148633591 -25698048 -520093961 -1209 133169151
            -103812348 -721428481</internalNodes>
          <leafValues>
            -6.5783321857452393e-01 1.9410495460033417e-01</leafValues></_>
        <_>
          <internalNodes>
            0 -1 61 -717179948 -9374236 -581713921 -1076841616
            1323720701 -1081549914 -272744449 722468864</internalNodes>
          <leafValues>
            -5.6369322538375854e-01 2.9236978292465210e-01</leafValues></_>
        <_>
          <internalNodes>
            0 -1 3 -500750814 -487627273 -2131735954 -87102706
            1969713956 1618695899 1989624053 -135793865</internalNodes>
          <leafValues>
            -5.4797309637069702e-01 3.1121733784675598e-01</leafValues></_>
        <_>
          <internalNodes>
            0 -1 57 4194384 2113868221 -45051395 -2157229 -722703681
            -67236929 -1155745027 4204544</internalNodes>
          <leafValues>
            -7.6136893033981323e-01 2.4244518578052521e-01</leafValues></_>
        <_>
          <internalNodes>
            0 -1 102 -203491074 836792416 978849880 980465884 333488593
            282654613 -1029668628 -335545601</internalNodes>
          <leafValues>
            -4.4871535897254944e-01 3.8452658057212830e-01</leafValues></_>
        <_>
          <internalNodes>
            0 -1 24 -1757501443 -1076483905 -1653865985 1067193105
            704908280 -1076312132 -105239847 -1090905634</internalNodes>
          <leafValues>
            -4.0212839841842651e-01 4.5655438303947449e-01</leafValues></_>
        <_>
          <internalNodes>
            0 -1 93 -68224350 -498997469 -723851742 -1331496190
            1637503309 1101152343 1908400422 -168296449</internalNodes>
          <leafValues>
            -5.0145322084426880e-01 3.3501255512237549e-01</leafValues></_>
        <_>
          <internalNodes>
            0 -1 15 -545370627 -78245 -444461090 -1096931590 199758333
            1310203059 1331437533 1566725100</internalNodes>
          <leafValues>
            -5.0831568241119385e-01 3.5741838812828064e-01</leafValues></_></weakClassifiers></_>
    <!-- stage 8 -->
    <_>
      <maxWeakCount>8</maxWeakCount>
      <stageThreshold>-1.0506174564361572e+00</stageThreshold>
      <weakClassifiers>
        <_>
          <internalNodes>
            0 -1 124 -67109109 1113576183 -14160600 -924854433
            -341836020 382462907 -69206268 -184549381</internalNodes>
          <leafValues>
            -6.0169494152069092e-01 2.2098569571971893e-01</leafValues></_>
        <_>
          <internalNodes>
            0 -1 55 -1073512445 -788345853 74174129 -105666001
            -632894997 -1073630138 -1046500353 -1055932277</internalNodes>
          <leafValues>
            -4.1919940710067749e-01 4.3400409817695618e-01</leafValues></_>
        <_>
          <internalNodes>
            0 -1 99 -1066933725 -169871541 -2047083273 -176820373
            -1194670898 -2002588448 -532938753 -1071120757</internalNodes>
          <leafValues>
            -3.4907507896423340e-01 4.8660326004028320e-01</leafValues></_>
        <_>
          <internalNodes>
            0 -1 44 770194932 532454301 -155316322 536753624 532750332
            -1617090311 999832316 1072434316</internalNodes>
          <leafValues>
            -7.5946396589279175e-01 2.3567344248294830e-01</leafValues></_>
        <_>
          <internalNodes>
            0 -1 8 -858790034 1759166227 -390697462 -84152498 2003005808
            1459833890 -244295820 1970765431</internalNodes>
          <leafValues>
            -7.4084985256195068e-01 2.1838405728340149e-01</leafValues></_>
        <_>
          <internalNodes>
            0 -1 30 268440317 2069442837 291833788 899196306 1688807419
            440540331 1403083432 870126063</internalNodes>
          <leafValues>
            -5.8843880891799927e-01 2.9690697789192200e-01</leafValues></_>
        <_>
          <internalNodes>
            0 -1 118 264220423 137016315 -883978220 -1712087557
            -539766463 1084217535 -325453368 -457179137</internalNodes>
          <leafValues>
            -5.0881922245025635e-01 3.2800257205963135e-01</leafValues></_>
        <_>
          <internalNodes>
            0 -1 84 -492052222 -746653870 -992126635 -5251052
            -1417702965 -1599993849 -477111705 1074258246</internalNodes>
          <leafValues>
            -4.9887087941169739e-01 3.7321901321411133e-01</leafValues></_></weakClassifiers></_>
    <!-- stage 9 -->
    <_>
      <maxWeakCount>9</maxWeakCount>
      <stageThreshold>-1.0952166318893433e+00</stageThreshold>
      <weakClassifiers>
        <_>
          <internalNodes>
            0 -1 14 -67174401 -341121 -747439362 -2959238 1588467868
            1540575161 -359706659 -537763845</internalNodes>
          <leafValues>
            -5.1352906227111816e-01 3.3938100934028625e-01</leafValues></_>
        <_>
          <internalNodes>
            0 -1 94 -2098946 1524162928 480250392 2084999728 1539835836
            410534280 1382295996 -1041</internalNodes>
          <leafValues>
            -4.2444497346878052e-01 3.6781191825866699e-01</leafValues></_>
        <_>
          <internalNodes>
            0 -1 106 -2106421449 -32833 -4169 -1150550021 -1095325697
            -16777254 -69633 -1367203038</internalNodes>
          <leafValues>
            -3.5375756025314331e-01 4.4176253676414490e-01</leafValues></_>
        <_>
          <internalNodes>
            0 -1 74 -211830852 977036212 -1324474212 466099646
            1531197468 693137649 1966932760 2147483611</internalNodes>
          <leafValues>
            -5.3484636545181274e-01 2.9696145653724670e-01</leafValues></_>
        <_>
          <internalNodes>
            0 -1 53 -395318034 -466107909 -804811776 -218127710
            1433621701 1155756407 -1272463945 -201328641</internalNodes>
          <leafValues>
            -4.2170733213424683e-01 3.7720391154289246e-01</leafValues></_>
        <_>
          <internalNodes>
            0 -1 19 -397670742 -1612936999 -1076229793 1071130368
            689441036 -347459953 1504251647 -69385219</internalNodes>
          <leafValues>
            -5.1462930440902710e-01 2.9735124111175537e-01</leafValues></_>
        <_>
          <internalNodes>
            0 -1 105 -8716872 998558710 -1756428132 1057791154 728858552
            759925180 1240457188 -1343503809</internalNodes>
          <leafValues>
            -4.3214339017868042e-01 3.7407690286636353e-01</leafValues></_>
        <_>
          <internalNodes>
            0 -1 0 713953058 -8196014 1102445911 1462899456 1750480879
            -70002273 -414456321 1164398675</internalNodes>
          <leafValues>
            -5.9928321838378906e-01 2.5606244802474976e-01</leafValues></_>
        <_>
          <internalNodes>
            0 -1 101 -1023423481 16438302 -782775987 1414519651
            2036583974 1082048647 -815796477 1149231087</internalNodes>
          <leafValues>
            -5.1024430990219116e-01 3.2512000203132629e-01</leafValues></_></weakClassifiers></_>
    <!-- stage 10 -->
    <_>
      <maxWeakCount>9</maxWeakCount>
      <stageThreshold>-1.2098878622055054e+00</stageThreshold>
      <weakClassifiers>
        <_>
          <internalNodes>
            0 -1 114 828129277 1073495037 902635005 996941529 2139963389
            -1074492688 1073420797 -1073992196</internalNodes>
          <leafValues>
            -6.4098429679870605e-01 1.5371209383010864e-01</leafValues></_>
        <_>
          <internalNodes>
            0 -1 98 -2001852559 -1652591777 -549464097 -1075370221
            -1176567876 -4218881 -678250309 -1474166784</internalNodes>
          <leafValues>
            -4.6904677152633667e-01 3.1162470579147339e-01</leafValues></_>
        <_>
          <internalNodes>
            0 -1 96 -285506 -72338470 -118159272 1063598842 2062815416
            755249356 1843205868 2139093755</internalNodes>
          <leafValues>
            -4.9528336524963379e-01 3.1505000591278076e-01</leafValues></_>
        <_>
          <internalNodes>
            0 -1 12 -428880145 -298400305 -433412890 -288428378
            1406629637 -210544355 -178239196 -134875321</internalNodes>
          <leafValues>
            -4.5534977316856384e-01 3.5366109013557434e-01</leafValues></_>
        <_>
          <internalNodes>
            0 -1 50 1076150005 1576308661 1966390781 -41992271
            -1327710548 -1177534499 938254335 -1358152824</internalNodes>
          <leafValues>
            -3.7629887461662292e-01 4.3275776505470276e-01</leafValues></_>
        <_>
          <internalNodes>
            0 -1 72 -1073233406 -212621525 -753454245 -172756878
            -970474517 -1919709 1777054207 -467142777</internalNodes>
          <leafValues>
            -4.2834660410881042e-01 3.8237318396568298e-01</leafValues></_>
        <_>
          <internalNodes>
            0 -1 70 -1104674384 159417284 -1370474053 -1852796492
            -106169864 -39286580 683543517 -1449321120</internalNodes>
          <leafValues>
            -5.5155992507934570e-01 2.6364430785179138e-01</leafValues></_>
        <_>
          <internalNodes>
            0 -1 67 -873476314 1531589507 -233729446 1455866726
            -879542507 1427460699 -310958112 -175972465</internalNodes>
          <leafValues>
            -4.8735302686691284e-01 3.2814309000968933e-01</leafValues></_>
        <_>
          <internalNodes>
            0 -1 17 -167824420 529301702 286274006 -1076292717
            -731073828 361802184 -1513342056 1776401834</internalNodes>
          <leafValues>
            -5.2737045288085938e-01 3.0997651815414429e-01</leafValues></_></weakClassifiers></_>
    <!-- stage 11 -->
    <_>
      <maxWeakCount>10</maxWeakCount>
      <stageThreshold>-1.0168726444244385e+00</stageThreshold>
      <weakClassifiers>
        <_>
          <internalNodes>
            0 -1 2 -282105049 1854882015 -763108866 -24315162 1077237623
            1593999391 -68683819 -134745097</internalNodes>
          <leafValues>
            -5.6601125001907349e-01 1.8559999763965607e-01</leafValues></_>
        <_>
          <internalNodes>
            0 -1 25 -1069658863 -143960619 -100935745 -2107053 -82945
            -72356689 -909156629 -2002059260</internalNodes>
          <leafValues>
            -3.8864189386367798e-01 3.7928998470306396e-01</leafValues></_>
        <_>
          <internalNodes>
            0 -1 113 -1051844 403755324 2090136700 1026881812 -112328761
            479507756 -272697132 941618814</internalNodes>
          <leafValues>
            -5.2156370878219604e-01 2.7425044775009155e-01</leafValues></_>
        <_>
          <internalNodes>
            0 -1 64 -788467504 -112184752 1460884859 1964298582
            -249060385 -542400312 729492155 -611888945</internalNodes>
          <leafValues>
            -3.9346575736999512e-01 3.6530187726020813e-01</leafValues></_>
        <_>
          <internalNodes>
            0 -1 52 -163664932 931703872 1797007512 1066180504 929829884
            493879645 432876188 2113797612</internalNodes>
          <leafValues>
            -6.3601201772689819e-01 2.0326934754848480e-01</leafValues></_>
        <_>
          <internalNodes>
            0 -1 89 -269490390 1153909735 -1056250586 1924030858
            323638037 1083437111 -148909884 -744489985</internalNodes>
          <leafValues>
            -4.4436231255531311e-01 3.1746098399162292e-01</leafValues></_>
        <_>
          <internalNodes>
            0 -1 80 -1030758398 -1619279070 -1793862817 2008020225
            -85087332 -627838142 -243282482 1661989193</internalNodes>
          <leafValues>
            -4.6089529991149902e-01 2.8434169292449951e-01</leafValues></_>
        <_>
          <internalNodes>
            0 -1 47 1813451020 1060316989 -1281298465 1060333234
            -859403330 -22027843 -1790755684 -1474402292</internalNodes>
          <leafValues>
            -4.9409744143486023e-01 2.9811391234397888e-01</leafValues></_>
        <_>
          <internalNodes>
            0 -1 29 -620290014 -1682231266 21373082 429728255
            -1723004230 254347419 1539383790 -539496021</internalNodes>
          <leafValues>
            -4.2372927069664001e-01 3.5059794783592224e-01</leafValues></_>
        <_>
          <internalNodes>
            0 -1 91 1104627504 -202913830 567135735 1804026111 403270335
            -1417494079 4516271 1500482</internalNodes>
          <leafValues>
            -5.0134706497192383e-01 2.9041498899459839e-01</leafValues></_></weakClassifiers></_>
    <!-- stage 12 -->
    <_>
      <maxWeakCount>10</maxWeakCount>
      <stageThreshold>-1.3292946815490723e+00</stageThreshold>
      <weakClassifiers>
        <_>
          <internalNodes>
            0 -1 126 -8397891 1059715566 -284174916 -1089735083
            -71309331 993783025 -1615692 -1119882243</internalNodes>
          <leafValues>
            -5.1894056797027588e-01 2.5559258460998535e-01</leafValues></_>
        <_>
          <internalNodes>
            0 -1 117 268406023 16512863 -883751412 -1937838283
            1508900115 211490699 -2254104 -1730678849</internalNodes>
          <leafValues>
            -4.8317861557006836e-01 2.8284984827041626e-01</leafValues></_>
        <_>
          <internalNodes>
            0 -1 41 996949948 -1074251786 -1927935233 -1076350024
            2075671804 -1142087780 1073228796 419182780</internalNodes>
          <leafValues>
            -6.7560386657714844e-01 1.9361333549022675e-01</leafValues></_>
        <_>
          <internalNodes>
            0 -1 34 285159670 1574877663 812781612 902735252 1349253615
            501624074 1660812238 837135102</internalNodes>
          <leafValues>
            -5.5906951427459717e-01 2.4412161111831665e-01</leafValues></_>
        <_>
          <internalNodes>
            0 -1 87 -401964542 -604282584 -238832173 -201336817
            407841743 -1952461093 537912235 1076871682</internalNodes>
          <leafValues>
            -4.8815396428108215e-01 2.8597831726074219e-01</leafValues></_>
        <_>
          <internalNodes>
            0 -1 13 -319827993 -336706129 -464467252 -355808542
            1880126391 2065129619 1637237623 -170393849</internalNodes>
          <leafValues>
            -4.3116512894630432e-01 3.1429883837699890e-01</leafValues></_>
        <_>
          <internalNodes>
            0 -1 58 -1082594312 2001260664 -1714419576 462032044
            504642296 940394525 238295292 2140786687</internalNodes>
          <leafValues>
            -5.9527158737182617e-01 2.5428023934364319e-01</leafValues></_>
        <_>
          <internalNodes>
            0 -1 107 -536875509 -290797713 -836580346 1937303703
            -1143021729 1079230851 -241961232 -201326593</internalNodes>
          <leafValues>
            -3.8347908854484558e-01 3.8469237089157104e-01</leafValues></_>
        <_>
          <internalNodes>
            0 -1 76 24948468 1439961976 117965308 394148762 824443848
            355535340 1576580607 2147105023</internalNodes>
          <leafValues>
            -5.8180338144302368e-01 2.6587575674057007e-01</leafValues></_>
        <_>
          <internalNodes>
            0 -1 79 -97412 705625872 -1928719736 991174672 1991513048
            340794318 132452816 2074410985</internalNodes>
          <leafValues>
            -6.4737218618392944e-01 2.0131689310073853e-01</leafValues></_></weakClassifiers></_>
    <!-- stage 13 -->
    <_>
      <maxWeakCount>11</maxWeakCount>
      <stageThreshold>-1.3363951444625854e+00</stageThreshold>
      <weakClassifiers>
        <_>
          <internalNodes>
            0 -1 119 -1210061049 239064501 1036498688 48232447 -91241205
            1571810027 -274466048 -234881025</internalNodes>
          <leafValues>
            -5.9806686639785767e-01 1.1762652546167374e-01</leafValues></_>
        <_>
          <internalNodes>
            0 -1 116 -2072027132 1499457101 1561809911 -608176129
            -823149942 -811340033 15530634 14679843</internalNodes>
          <leafValues>
            -4.8367556929588318e-01 2.6368728280067444e-01</leafValues></_>
        <_>
          <internalNodes>
            0 -1 26 -947640228 -5240282 1397146301 -1817464 -113215576
            -276022548 -1142185266 721682944</internalNodes>
          <leafValues>
            -5.6088328361511230e-01 2.3705115914344788e-01</leafValues></_>
        <_>
          <internalNodes>
            0 -1 83 -939475964 -1630259847 -1163364107 896693461
            -1129545224 -1163337043 -1131627606 -1476257760</internalNodes>
          <leafValues>
            -4.8416930437088013e-01 2.7785962820053101e-01</leafValues></_>
        <_>
          <internalNodes>
            0 -1 1 -286265553 -2097172889 -1360007282 -810752504
            1945337719 931133431 2138466151 -134752411</internalNodes>
          <leafValues>
            -3.6276057362556458e-01 3.7057456374168396e-01</leafValues></_>
        <_>
          <internalNodes>
            0 -1 104 -1140933122 -1720043790 -1426186882 968100792
            -1159066977 -273792711 -1077401116 -1111601445</internalNodes>
          <leafValues>
            -3.9298012852668762e-01 3.4287840127944946e-01</leafValues></_>
        <_>
          <internalNodes>
            0 -1 95 -495991805 1207847255 553108994 2004613963
            1695536911 125740555 1655957479 -204484689</internalNodes>
          <leafValues>
            -3.9670366048812866e-01 3.5816499590873718e-01</leafValues></_>
        <_>
          <internalNodes>
            0 -1 69 268572211 -1157685379 228540413 -1246281740
            1073065723 -1073840132 -318914561 -104598310</internalNodes>
          <leafValues>
            -3.4255403280258179e-01 4.1352078318595886e-01</leafValues></_>
        <_>
          <internalNodes>
            0 -1 78 -401350528 -682952605 -767638169 -771264442
            -1383950964 -1412695392 -404776225 1345840138</internalNodes>
          <leafValues>
            -4.8042595386505127e-01 2.6937142014503479e-01</leafValues></_>
        <_>
          <internalNodes>
            0 -1 32 558182944 -1644488209 -774811301 -134234981
            -1848805381 -1147803949 -991183874 17965568</internalNodes>
          <leafValues>
            -6.9411402940750122e-01 1.7676301300525665e-01</leafValues></_>
        <_>
          <internalNodes>
            0 -1 54 -840311459 1472786284 329555577 494149437 851195388
            788428412 937691550 -67110145</internalNodes>
          <leafValues>
            -3.3304396271705627e-01 4.0314087271690369e-01</leafValues></_></weakClassifiers></_>
    <!-- stage 14 -->
    <_>
      <maxWeakCount>11</maxWeakCount>
      <stageThreshold>-1.5702900886535645e+00</stageThreshold>
      <weakClassifiers>
        <_>
          <internalNodes>
            0 -1 111 -1056985201 1089403863 -1396998657 -665986049
            1266152190 -860122726 -372251416 -1059062785</internalNodes>
          <leafValues>
            -5.3219449520111084e-01 2.0486110448837280e-01</leafValues></_>
        <_>
          <internalNodes>
            0 -1 4 782905099 -345065493 -1364269618 -353961782
            1393776415 1458043255 -174820621 -142609545</internalNodes>
          <leafValues>
            -4.9447891116142273e-01 2.7227249741554260e-01</leafValues></_>
        <_>
          <internalNodes>
            0 -1 16 -606089254 925910490 -1241603426 -1076735762
            1561271512 1304250681 497303692 1862229930</internalNodes>
          <leafValues>
            -4.5629221200942993e-01 2.8698876500129700e-01</leafValues></_>
        <_>
          <internalNodes>
            0 -1 66 421704177 -1683952655 2147336159 -1082880013
            -1073823745 -6570049 -17024338 -84729486</internalNodes>
          <leafValues>
            -3.2299223542213440e-01 3.8597777485847473e-01</leafValues></_>
        <_>
          <internalNodes>
            0 -1 115 -1749207555 998775349 -1256514305 -35727521
            696089085 -1432598289 2043218169 -1610843912</internalNodes>
          <leafValues>
            -3.7526792287826538e-01 3.2450702786445618e-01</leafValues></_>
        <_>
          <internalNodes>
            0 -1 125 -545263849 -2146697218 -273416304 -50790418
            -1073746041 518324222 -33554784 -658514289</internalNodes>
          <leafValues>
            -3.2420372962951660e-01 4.0965199470520020e-01</leafValues></_>
        <_>
          <internalNodes>
            0 -1 100 -487594453 2026893416 387177215 1354210610
            -1031015122 -17247836 1084028367 1074782986</internalNodes>
          <leafValues>
            -3.6092731356620789e-01 3.6433976888656616e-01</leafValues></_>
        <_>
          <internalNodes>
            0 -1 35 2146353144 903648761 -712436227 1031184125
            1368192253 1252083485 836306618 981267180</internalNodes>
          <leafValues>
            -5.4808396100997925e-01 2.0727691054344177e-01</leafValues></_>
        <_>
          <internalNodes>
            0 -1 39 -233848605 -142739610 -1384235451 2012741235
            -169505029 -361580766 1374625758 -531115930</internalNodes>
          <leafValues>
            -2.8540691733360291e-01 4.3118214607238770e-01</leafValues></_>
        <_>
          <internalNodes>
            0 -1 59 -270344964 2008479958 -822079716 727650460 -45194244
            356275355 1602885720 2112421631</internalNodes>
          <leafValues>
            -4.5606413483619690e-01 2.6479825377464294e-01</leafValues></_>
        <_>
          <internalNodes>
            0 -1 62 -1419078664 2077620909 -845475078 -206014116
            999095034 1532497066 749717756 -5257234</internalNodes>
          <leafValues>
            -3.8393145799636841e-01 3.2824596762657166e-01</leafValues></_></weakClassifiers></_>
    <!-- stage 15 -->
    <_>
      <maxWeakCount>12</maxWeakCount>
      <stageThreshold>-1.1136264801025391e+00</stageThreshold>
      <weakClassifiers>
        <_>
          <internalNodes>
            0 -1 14 -9 -69633 -68485377 -68485446 -172801 -536912001
            -9151014 -8193</internalNodes>
          <leafValues>
            -3.9596679806709290e-01 4.5984113216400146e-01</leafValues></_>
        <_>
          <internalNodes>
            0 -1 9 -269524181 1315914701 -858338706 -361857298
            2002220407 1699956499 -674278799 -143199305</internalNodes>
          <leafValues>
            -5.1690953969955444e-01 2.3336707055568695e-01</leafValues></_>
        <_>
          <internalNodes>
            0 -1 85 -71849286 -14009750 2131167292 458173998 653927322
            786276819 1088952524 2131229663</internalNodes>
          <leafValues>
            -4.5092019438743591e-01 2.6860737800598145e-01</leafValues></_>
        <_>
          <internalNodes>
            0 -1 18 -1566387536 958398750 -581927144 -1256505505
            -1781490504 -1456848172 -109045320 -304088401</internalNodes>
          <leafValues>
            -3.4108951687812805e-01 3.7153768539428711e-01</leafValues></_>
        <_>
          <internalNodes>
            0 -1 103 -16386 905453757 -216293961 -1073858611 2079972863
            532715673 -24035334 2079799231</internalNodes>
          <leafValues>
            -3.9286559820175171e-01 3.1003287434577942e-01</leafValues></_>
        <_>
          <internalNodes>
            0 -1 82 -405325320 1939030768 -1882900744 931836032
            2052894872 1029559721 1202524362 2134900734</internalNodes>
          <leafValues>
            -4.3752536177635193e-01 3.0235156416893005e-01</leafValues></_>
        <_>
          <internalNodes>
            0 -1 65 136184849 -42524502 1633233907 1608993695 182426623
            -1095793527 -1241308989 -1439178069</internalNodes>
          <leafValues>
            -4.3183043599128723e-01 3.1226927042007446e-01</leafValues></_>
        <_>
          <internalNodes>
            0 -1 46 -745823581 -214436743 -49470563 -542269649
            -295853061 -859714261 -876231724 -1073233150</internalNodes>
          <leafValues>
            -3.1300574541091919e-01 3.9668017625808716e-01</leafValues></_>
        <_>
          <internalNodes>
            0 -1 109 -1129675012 1066538866 -1387787522 1062903642
            -208723715 -1680193895 -1143404520 -1597050436</internalNodes>
          <leafValues>
            -4.1765916347503662e-01 3.0734732747077942e-01</leafValues></_>
        <_>
          <internalNodes>
            0 -1 40 -890510834 1831795832 -236676776 12903158 649249679
            1074421867 -1339824180 -481820721</internalNodes>
          <leafValues>
            -4.0710410475730896e-01 3.0864900350570679e-01</leafValues></_>
        <_>
          <internalNodes>
            0 -1 21 -46191328 1971318713 -1 -100697553 -295768067
            -16777345 -1107521650 -391648248</internalNodes>
          <leafValues>
            -3.1451034545898438e-01 4.0722864866256714e-01</leafValues></_>
        <_>
          <internalNodes>
            0 -1 38 -128975033 -785907845 -1979322433 464517451
            -1665863986 -18882562 539409374 -937178073</internalNodes>
          <leafValues>
            -2.8620451688766479e-01 4.5744663476943970e-01</leafValues></_></weakClassifiers></_></stages>
  <features>
    <_>
      <rect>
        0 0 1 1</rect></_>
    <_>
      <rect>
        0 1 1 1</rect></_>
    <_>
      <rect>
        0 2 1 2</rect></_>
    <_>
      <rect>
        0 2 1 3</rect></_>
    <_>
      <rect>
        0 4 1 1</rect></_>
    <_>
      <rect>
        0 5 1 1</rect></_>
    <_>
      <rect>
        0 5 1 2</rect></_>
    <_>
      <rect>
        0 6 1 1</rect></_>
    <_>
      <rect>
        0 6 2 2</rect></_>
    <_>
      <rect>
        0 7 1 1</rect></_>
    <_>
      <rect>
        0 8 1 2</rect></_>
    <_>
      <rect>
        0 10 1 2</rect></_>
    <_>
      <rect>
        0 12 1 1</rect></_>
    <_>
      <rect>
        0 13 1 1</rect></_>
    <_>
      <rect>
        0 15 1 1</rect></_>
    <_>
      <rect>
        0 15 2 1</rect></_>
    <_>
      <rect>
        0 15 3 1</rect></_>
    <_>
      <rect>
        0 15 12 1</rect></_>
    <_>
      <rect>
        1 1 4 2</rect></_>
    <_>
      <rect>
        1 2 6 1</rect></_>
    <_>
      <rect>
        1 2 8 1</rect></_>
    <_>
      <rect>
        2 0 2 1</rect></_>
    <_>
      <rect>
        2 0 8 1</rect></_>
    <_>
      <rect>
        2 12 9 1</rect></_>
    <_>
      <rect>
        2 15 6 1</rect></_>
    <_>
      <rect>
        3 0 2 1</rect></_>
    <_>
      <rect>
        3 4 8 1</rect></_>
    <_>
      <rect>
        3 13 7 1</rect></_>
    <_>
      <rect>
        4 0 3 1</rect></_>
    <_>
      <rect>
        4 9 9 2</rect></_>
    <_>
      <rect>
        5 2 8 1</rect></_>
    <_>
      <rect>
        5 14 7 1</rect></_>
    <_>
      <rect>
        6 0 1 1</rect></_>
    <_>
      <rect>
        6 0 4 1</rect></_>
    <_>
      <rect>
        6 1 8 1</rect></_>
    <_>
      <rect>
        6 15 1 1</rect></_>
    <_>
      <rect>
        6 15 6 1</rect></_>
    <_>
      <rect>
        7 0 8 2</rect></_>
    <_>
      <rect>
        7 3 4 2</rect></_>
    <_>
      <rect>
        7 4 7 2</rect></_>
    <_>
      <rect>
        9 9 1 1</rect></_>
    <_>
      <rect>
        9 15 2 1</rect></_>
    <_>
      <rect>
        10 0 1 4</rect></_>
    <_>
      <rect>
        10 0 8 1</rect></_>
    <_>
      <rect>
        10 15 3 1</rect></_>
    <_>
      <rect>
        10 15 6 1</rect></_>
    <_>
      <rect>
        11 0 1 3</rect></_>
    <_>
      <rect>
        11 0 8 1</rect></_>
    <_>
      <rect>
        11 2 6 2</rect></_>
    <_>
      <rect>
        11 3 8 1</rect></_>
    <_>
      <rect>
        11 13 6 1</rect></_>
    <_>
      <rect>
        12 3 6 1</rect></_>
    <_>
      <rect>
        12 6 1 4</rect></_>
    <_>
      <rect>
        12 9 2 1</rect></_>
    <_>
      <rect>
        12 11 1 2</rect></_>
    <_>
      <rect>
        13 0 1 3</rect></_>
    <_>
      <rect>
        13 0 1 4</rect></_>
    <_>
      <rect>
        13 0 4 1</rect></_>
    <_>
      <rect>
        13 8 2 3</rect></_>
    <_>
      <rect>
        13 9 1 2</rect></_>
    <_>
      <rect>
        14 0 4 1</rect></_>
    <_>
      <rect>
        14 4 5 1</rect></_>
    <_>
      <rect>
        14 8 2 3</rect></_>
    <_>
      <rect>
        14 15 4 1</rect></_>
    <_>
      <rect>
        15 2 5 2</rect></_>
    <_>
      <rect>
        15 3 1 1</rect></_>
    <_>
      <rect>
        15 3 4 1</rect></_>
    <_>
      <rect>
        15 10 2 1</rect></_>
    <_>
      <rect>
        16 3 4 1</rect></_>
    <_>
      <rect>
        17 3 1 1</rect></_>
    <_>
      <rect>
        18 3 4 1</rect></_>
    <_>
      <rect>
        18 15 3 1</rect></_>
    <_>
      <rect>
        19 0 1 4</rect></_>
    <_>
      <rect>
        19 5 1 3</rect></_>
    <_>
      <rect>
        19 6 1 4</rect></_>
    <_>
      <rect>
        19 9 1 1</rect></_>
    <_>
      <rect>
        19 11 2 2</rect></_>
    <_>
      <rect>
        20 1 1 3</rect></_>
    <_>
      <rect>
        20 2 1 3</rect></_>
    <_>
      <rect>
        20 9 1 2</rect></_>
    <_>
      <rect>
        21 1 1 4</rect></_>
    <_>
      <rect>
        21 6 1 4</rect></_>
    <_>
      <rect>
        21 7 1 3</rect></_>
    <_>
      <rect>
        21 13 3 1</rect></_>
    <_>
      <rect>
        22 1 1 4</rect></_>
    <_>
      <rect>
        22 7 1 3</rect></_>
    <_>
      <rect>
        23 0 1 4</rect></_>
    <_>
      <rect>
        23 3 1 2</rect></_>
    <_>
      <rect>
        23 7 1 3</rect></_>
    <_>
      <rect>
        23 9 1 1</rect></_>
    <_>
      <rect>
        24 0 1 4</rect></_>
    <_>
      <rect>
        24 0 4 1</rect></_>
    <_>
      <rect>
        24 6 1 4</rect></_>
    <_>
      <rect>
        24 9 1 1</rect></_>
    <_>
      <rect>
        24 9 1 3</rect></_>
    <_>
      <rect>
        25 6 1 1</rect></_>
    <_>
      <rect>
        25 6 1 4</rect></_>
    <_>
      <rect>
        25 8 1 3</rect></_>
    <_>
      <rect>
        27 0 2 1</rect></_>
    <_>
      <rect>
        27 1 1 3</rect></_>
    <_>
      <rect>
        27 2 1 3</rect></_>
    <_>
      <rect>
        27 5 3 2</rect></_>
    <_>
      <rect>
        27 9 1 3</rect></_>
    <_>
      <rect>
        27 15 1 1</rect></_>
    <_>
      <rect>
        27 15 2 1</rect></_>
    <_>
      <rect>
        27 15 3 1</rect></_>
    <_>
      <rect>
        28 0 2 1</rect></_>
    <_>
      <rect>
        28 7 1 1</rect></_>
    <_>
      <rect>
        28 9 1 1</rect></_>
    <_>
      <rect>
        28 15 1 1</rect></_>
    <_>
      <rect>
        30 0 2 3</rect></_>
    <_>
      <rect>
        30 1 2 3</rect></_>
    <_>
      <rect>
        30 1 2 4</rect></_>
    <_>
      <rect>
        30 12 2 2</rect></_>
    <_>
      <rect>
        31 15 1 1</rect></_>
    <_>
      <rect>
        32 15 1 1</rect></_>
    <_>
      <rect>
        33 0 1 1</rect></_>
    <_>
      <rect>
        33 1 1 2</rect></_>
    <_>
      <rect>
        33 2 1 2</rect></_>
    <_>
      <rect>
        33 5 1 1</rect></_>
    <_>
      <rect>
        33 6 1 1</rect></_>
    <_>
      <rect>
        33 6 1 2</rect></_>
    <_>
      <rect>
        33 8 1 2</rect></_>
    <_>
      <rect>
        33 9 1 1</rect></_>
    <_>
      <rect>
        33 11 1 1</rect></_>
    <_>
      <rect>
        33 11 1 2</rect></_>
    <_>
      <rect>
        33 15 1 1</rect></_></features></cascade>
</opencv_storage>
